wordslicer/__init__.py
wordslicer-0.1.0.dist-info/LICENSE
wordslicer-0.1.0.dist-info/METADATA
wordslicer-0.1.0.dist-info/WHEEL
wordslicer-0.1.0.dist-info/top_level.txt
wordslicer-0.1.0.dist-info/RECORD
