Metadata-Version: 2.1
Name: wordslicer
Version: 0.1.0
Summary: A tool to separate truncated text.
Home-page: https://github.com/bishop19/wordslicer
Author: Pedro Moreira, Nelson Sousa
Author-email: a82364@alunos.uminho.pt, a82053@alunos.uminho.pt
License: UNKNOWN
Platform: UNKNOWN
Classifier: Programming Language :: Python :: 3
Classifier: License :: OSI Approved :: MIT License
Classifier: Operating System :: OS Independent
